sminterp/ConvexSmooth.py
sminterp/LocalSmoothInterpolator.py
sminterp/__init__.py
sminterp-2021.9.9.dist-info/LICENSE
sminterp-2021.9.9.dist-info/METADATA
sminterp-2021.9.9.dist-info/WHEEL
sminterp-2021.9.9.dist-info/top_level.txt
sminterp-2021.9.9.dist-info/RECORD
