Metadata-Version: 2.1
Name: sminterp
Version: 2021.9.9
Summary: Smooth interpolators package
Home-page: https://github.com/RIVOIRA/smooth-interpolator
Author: Arnaud RIVOIRA
Author-email: arnaud.rivoira@gmail.com
License: UNKNOWN
Project-URL: Bug Tracker, https://github.com/RIVOIRA/smooth-interpolator/issues
Platform: UNKNOWN
Classifier: Programming Language :: Python :: 3
Classifier: License :: OSI Approved :: MIT License
Classifier: Operating System :: OS Independent
Requires-Python: >=3.6
License-File: LICENSE
